pysynapse/__init__.py
pysynapse/__version__.py
pysynapse/endpoints.py
pysynapse/exceptions.py
pysynapse/py.typed
pysynapse-0.0.3.dist-info/LICENSE
pysynapse-0.0.3.dist-info/METADATA
pysynapse-0.0.3.dist-info/WHEEL
pysynapse-0.0.3.dist-info/top_level.txt
pysynapse-0.0.3.dist-info/RECORD
