Metadata-Version: 2.1
Name: pysynapse
Version: 0.0.3
Summary: Python Synapse (Matrix) server Admin API module.
Author-email: Joe Pitt <joe.pitt@joepitt.co.uk>
License: GNU GENERAL PUBLIC LICENSE
Project-URL: Source, https://github.com/joepitt91/pysynapse
Classifier: Development Status :: 2 - Pre-Alpha
Classifier: Intended Audience :: System Administrators
Classifier: License :: OSI Approved :: GNU General Public License v3 (GPLv3)
Classifier: Natural Language :: English
Classifier: Operating System :: OS Independent
Classifier: Programming Language :: Python :: 3
Classifier: Topic :: Communications :: Chat
Classifier: Typing :: Typed
Requires-Python: ~=3.8
License-File: LICENSE
Requires-Dist: requests ~=2.32.3
Requires-Dist: validators ~=0.28.3
